[
    {
        "text": "hello there"
    },
    {
        "text": "this is a link",
        "link": "https://youtube.com"
    },
    {
        "text": "this is a header",
        "link": "https://youtube.com",
        "children": [
            {
                "text": "this is a child"
            },
            {
                "text": "this is a header",
                "children": [
                    {
                        "text": "this is a child",
                        "link": "https://youtube.com"
                    }
                ]
            }
        ]
    },
    {
        "text": "this is a header",
        "link": "https://youtube.com",
        "children": [
            {
                "text": "this is a child"
            },
            {
                "text": "this is a header",
                "children": [
                    {
                        "text": "this is a child",
                        "link": "https://youtube.com"
                    }
                ]
            }
        ]
    }
]